jsonflow/__init__.py
jsonflow/core/__init__.py
jsonflow/core/executor.py
jsonflow/core/operator.py
jsonflow/core/pipeline.py
jsonflow/io/__init__.py
jsonflow/io/loader.py
jsonflow/io/saver.py
jsonflow/operators/__init__.py
jsonflow/operators/json_ops/__init__.py
jsonflow/operators/json_ops/collection_ops.py
jsonflow/operators/json_ops/json_expr_ops.py
jsonflow/operators/json_ops/json_field_ops.py
jsonflow/operators/json_ops/json_filter.py
jsonflow/operators/json_ops/json_transformer.py
jsonflow/operators/json_ops/system_field_ops.py
jsonflow/operators/json_ops/text_normalizer.py
jsonflow/operators/model/__init__.py
jsonflow/operators/model/model_invoker.py
jsonflow/utils/__init__.py
jsonflow/utils/bos.py
jsonflow/utils/config.py
jsonflow/utils/logger.py
jsonflow/utils/operator_utils.py
jsonflow/utils/system_field.py
tests/__init__.py
tests/test_passthrough_fields.py
tests/test_system_fields.py
tests/utils/__init__.py
tests/utils/test_bos.py
guru4elephant_jsonflow-0.1.1.dist-info/METADATA
guru4elephant_jsonflow-0.1.1.dist-info/WHEEL
guru4elephant_jsonflow-0.1.1.dist-info/entry_points.txt
guru4elephant_jsonflow-0.1.1.dist-info/top_level.txt
guru4elephant_jsonflow-0.1.1.dist-info/RECORD
