Metadata-Version: 2.4
Name: guru4elephant-jsonflow
Version: 0.1.1
Summary: A library for processing JSON data with operators and pipelines
Home-page: https://github.com/guru4elephant/jsonflow
Author: JSONFlow Contributors
Author-email: gongweibao@gmail.com
Classifier: Programming Language :: Python :: 3
Classifier: License :: OSI Approved :: MIT License
Classifier: Operating System :: OS Independent
Requires-Python: >=3.6
Requires-Dist: openai>=0.27.0
Provides-Extra: dev
Requires-Dist: pytest>=6.0; extra == "dev"
Requires-Dist: black; extra == "dev"
Requires-Dist: flake8; extra == "dev"
Requires-Dist: pytest-cov; extra == "dev"
Provides-Extra: bos
Requires-Dist: bce-python-sdk>=0.8.0; extra == "bos"
Provides-Extra: all
Requires-Dist: bce-python-sdk>=0.8.0; extra == "all"
Requires-Dist: pytest>=6.0; extra == "all"
Requires-Dist: black; extra == "all"
Requires-Dist: flake8; extra == "all"
Requires-Dist: pytest-cov; extra == "all"
Dynamic: author
Dynamic: author-email
Dynamic: classifier
Dynamic: description
Dynamic: description-content-type
Dynamic: home-page
Dynamic: provides-extra
Dynamic: requires-dist
Dynamic: requires-python
Dynamic: summary
